dserver/__init__.py
dserver/__main__.py
dserver/main.py
dserver/utils.py
sserver/__init__.py
sserver/__main__.py
sserver/filters.py
sserver/main.py
sserver/model.py
sserver/utils.py
sserver/templates/index.html
sserver/templates/media.html
sserver/templates/message.html
sserver/upload/bootstrap-5.3.1.min.css
sserver/upload/bootstrap-5.3.1.min.js
sserver/upload/favicon.ico
sserver/upload/jquery-3.7.1.js
sserver/upload/jquery-3.7.1.min.js
dserver-0.2.8.dist-info/METADATA
dserver-0.2.8.dist-info/WHEEL
dserver-0.2.8.dist-info/top_level.txt
dserver-0.2.8.dist-info/RECORD
